{"About":{"FIPS":"13037","State":"Georgia","Population":"","County":"Calhoun"},"Premature Death":{"Unreliable":"","Deaths":115,"Years of Potential Life Lost Rate":7844.3},"Poor or Fair Health":{"% Fair or Poor Health":25.5},"Poor Physical Health Days":{"Average Number of Physically Unhealthy Days":4.52},"Poor Mental Health Days":{"Average Number of Mentally Unhealthy Days":5.01},"Low Birthweight":{"Unreliable":"","% Low Birthweight":10.98},"Adult Smoking":{"% Adults Reporting Currently Smoking":26},"Adult Obesity":{"% Adults with Obesity":44.2},"Food Environment Index":{"Food Environment Index":7.3},"Physical Inactivity":{"% Physically Inactive":36.4},"Access to Exercise Opportunities":{"% With Access to Exercise Opportunities":""},"Excessive Drinking":{"% Excessive Drinking":14.64},"Alcohol-Impaired Driving Deaths":{"# Alcohol-Impaired Driving Deaths":1,"# Driving Deaths":8,"% Driving Deaths with Alcohol Involvement":12.5},"Sexually Transmitted Infections":{"# Chlamydia Cases":46,"Chlamydia Rate":743.3},"Teen Births":{"Teen Birth Rate":37.14},"Uninsured":{"Number of Uninsured":579,"Percent of Total Population Uninsured":17.01},"Primary Care Physicians":{"# Primary Care Physicians":1,"Primary Care Physicians Rate":16.05,"Primary Care Physicians Ratio":"6231:1"},"Dentists":{"# Dentists":2,"Dentist Rate":36.3,"Dentist Ratio":"2755:1"},"Mental Health Providers":{"# Mental Health Providers":1,"Mental Health Provider Rate":18.15,"Mental Health Provider Ratio":"5509:1"},"Preventable Hospital Stays":{"Preventable Hospitalization Rate":4543},"Mammography Screening":{"% with Annual Mammogram":37},"Flu Vaccinations":{"% Vaccinated":36},"High School Completion":{"# Completed High School":3249,"Population":4243,"% Completed High School":76.57},"Some College":{"# Some College":715,"Population":1934,"% Some College":36.97},"Unemployment":{"# Unemployed":90,"Labor Force":2228,"% Unemployed":4.04},"Children in Poverty":{"% Children in Poverty":39.1},"Income Inequality":{"80th Percentile Income":85786,"20th Percentile Income":17324,"Income Ratio":4.95},"Children in Single-Parent Households":{"# Children in Single-Parent Households":435,"# Children in Households":965,"% Children in Single-Parent Households":45.08},"Social Associations":{"# Associations":7,"Social Association Rate":11.23},"Injury Deaths":{"# Injury Deaths":22,"Injury Death Rate":69.73},"Air Pollution - Particulate Matter":{"Average Daily PM2.5":9.3},"Drinking Water Violations":{"Presence of Water Violation":"No"},"Severe Housing Problems":{"% Severe Housing Problems":14.12,"Severe Housing Cost Burden":12.68,"Overcrowding":1.67,"Inadequate Facilities":0.86},"Driving Alone to Work":{"% Drive Alone to Work":82.34},"Long Commute - Driving Alone":{"# Workers who Drive Alone":1393,"% Long Commute - Drives Alone":40.1},"Life Expectancy":{"Life Expectancy":77.17},"Premature Age-Adjusted Mortality":{"# Deaths":115,"Age-Adjusted Death Rate":498.68},"Child Mortality":{"# Deaths":"","Child Mortality Rate":""},"Infant Mortality":{"# Deaths":"","Infant Mortality Rate":""},"Frequent Physical Distress":{"% Frequent Physical Distress":14.4},"Frequent Mental Distress":{"% Frequent Mental Distress":17},"Diabetes Prevalence":{"% Adults with Diabetes":17.1},"HIV Prevalence":{"# HIV Cases":29,"HIV Prevalence Rate":524.6},"Food Insecurity":{"# Food Insecure":890,"% Food Insecure":14.1},"Limited Access to Healthy Foods":{"# Limited Access to Healthy Foods":422.45,"% Limited Access to Healthy Foods":6.31},"Drug Overdose Deaths":{"# Drug Overdose Deaths":"","Drug Overdose Mortality Rate":""},"Insufficient Sleep":{"% Insufficient Sleep":43.3},"Uninsured Adults":{"# Uninsured Adults":500,"% Uninsured Adults":20.36},"Uninsured Children":{"# Uninsured Children":83,"% Uninsured Children":8.19},"Other Primary Care Providers":{"Other Primary Care Provider Rate":90.76,"Other Primary Care Provider Ratio":"1102:1"},"High School Graduation":{"Cohort Size":"","High School Graduation Rate":""},"Disconnected Youth":{"% Disconnected Youth":""},"Reading Scores":{"Average Grade Performance":2.45},"Math Scores":{"Average Grade Performance":2.47},"School Segregation":{"Segregation Index":0.31},"School Funding Adequacy":{"Spending per Pupil":14202,"School Funding Adequacy":-12781.14},"Gender Pay Gap":{"Women's Median Earnings":41688,"Men's Median Earnings":38819,"Gender Pay Gap":1.07},"Median Household Income":{"Median Household Income":38232},"Children Eligible for Free or Reduced Price Lunch":{"% Enrolled in Free or Reduced Lunch":77.44},"Residential Segregation - Black/White":{"Segregation Index":14.07},"Child Care Cost Burden":{"% Household Income Required for Child Care Expenses":28.65},"Child Care Centers":{"# Child Care Centers":3,"Child Care Centers per 1,000 Children":13.16},"Homicides":{"Homicide Rate":""},"Suicides":{"# Deaths":"","Suicide Rate, Age-Adjusted":"","Crude Rate":""},"Firearm Fatalities":{"# Firearm Fatalities":"","Firearm Fatalities Rate":""},"Motor Vehicle Crash Deaths":{"# Motor Vehicle Deaths":"","Motor Vehicle Mortality Rate":""},"Juvenile Arrests":{"Non-Petitioned Cases":"","Petitioned Cases":"","Denominator":500,"Juvenile Arrest Rate":""},"Voter Turnout":{"% Voter Turnout":43.97},"Census Participation":{"% Census Participation":37},"Traffic Volume":{"Traffic Volume":0},"Homeownership":{"# Homeowners":993,"% Homeowners":68.15},"Severe Housing Cost Burden":{"# Households with Severe Cost Burden":162,"% Households with Severe Cost Burden":12.39},"Broadband Access":{"% Households with Broadband Access":71.45,"# Households with Broadband Access":1041},"Population":{"Population":5509},"% Below 18 Years of Age":{"% Less than 18 Years of Age":16.25},"% 65 and Older":{"% 65 and Over":16.65},"% Non-Hispanic Black":{"# Black":3344,"% Black":60.7},"% American Indian or Alaska Native":{"# American Indian or Alaska Native":27,"% American Indian or Alaska Native":0.49},"% Asian":{"# Asian":58,"% Asian":1.05},"% Native Hawaiian or Other Pacific Islander":{"# Native Hawaiian or Other Pacific Islander":19,"% Native Hawaiian or Other Pacific Islander":0.34},"% Hispanic":{"# Hispanic":287,"% Hispanic":5.21},"% Non-Hispanic White":{"# Non-Hispanic White":1749,"% Non-Hispanic White":31.75},"% Not Proficient in English":{"# Not Proficient in English":91,"% Not Proficient in English":1.67},"% Female":{"% Female":38.7},"% Rural":{"# Rural Residents":6694,"% Rural":100}}