{"About":{"FIPS":"16041","State":"Idaho","Population":"","County":"Franklin"},"Premature Death":{"Unreliable":"","Deaths":124,"Years of Potential Life Lost Rate":6487.71},"Poor or Fair Health":{"% Fair or Poor Health":12.9},"Poor Physical Health Days":{"Average Number of Physically Unhealthy Days":3.27},"Poor Mental Health Days":{"Average Number of Mentally Unhealthy Days":4.14},"Low Birthweight":{"Unreliable":"","% Low Birthweight":8.27},"Adult Smoking":{"% Adults Reporting Currently Smoking":16.6},"Adult Obesity":{"% Adults with Obesity":34.8},"Food Environment Index":{"Food Environment Index":9.2},"Physical Inactivity":{"% Physically Inactive":22.7},"Access to Exercise Opportunities":{"% With Access to Exercise Opportunities":60.89},"Excessive Drinking":{"% Excessive Drinking":16.88},"Alcohol-Impaired Driving Deaths":{"# Alcohol-Impaired Driving Deaths":5,"# Driving Deaths":13,"% Driving Deaths with Alcohol Involvement":38.46},"Sexually Transmitted Infections":{"# Chlamydia Cases":21,"Chlamydia Rate":151.3},"Teen Births":{"Teen Birth Rate":15.84},"Uninsured":{"Number of Uninsured":1556,"Percent of Total Population Uninsured":12.95},"Primary Care Physicians":{"# Primary Care Physicians":5,"Primary Care Physicians Rate":35.17,"Primary Care Physicians Ratio":"2843:1"},"Dentists":{"# Dentists":7,"Dentist Rate":47.73,"Dentist Ratio":"2095:1"},"Mental Health Providers":{"# Mental Health Providers":8,"Mental Health Provider Rate":54.55,"Mental Health Provider Ratio":"1833:1"},"Preventable Hospital Stays":{"Preventable Hospitalization Rate":3247},"Mammography Screening":{"% with Annual Mammogram":33},"Flu Vaccinations":{"% Vaccinated":43},"High School Completion":{"# Completed High School":7774,"Population":8382,"% Completed High School":92.75},"Some College":{"# Some College":1421,"Population":3359,"% Some College":42.3},"Unemployment":{"# Unemployed":182,"Labor Force":7369,"% Unemployed":2.47},"Children in Poverty":{"% Children in Poverty":10.1},"Income Inequality":{"80th Percentile Income":112276,"20th Percentile Income":28894,"Income Ratio":3.89},"Children in Single-Parent Households":{"# Children in Single-Parent Households":333,"# Children in Households":4507,"% Children in Single-Parent Households":7.39},"Social Associations":{"# Associations":0,"Social Association Rate":0},"Injury Deaths":{"# Injury Deaths":52,"Injury Death Rate":75.6},"Air Pollution - Particulate Matter":{"Average Daily PM2.5":5.8},"Drinking Water Violations":{"Presence of Water Violation":"Yes"},"Severe Housing Problems":{"% Severe Housing Problems":11.6,"Severe Housing Cost Burden":8.33,"Overcrowding":2.62,"Inadequate Facilities":2.16},"Driving Alone to Work":{"% Drive Alone to Work":78.64},"Long Commute - Driving Alone":{"# Workers who Drive Alone":6387,"% Long Commute - Drives Alone":37.8},"Life Expectancy":{"Life Expectancy":79.18},"Premature Age-Adjusted Mortality":{"# Deaths":124,"Age-Adjusted Death Rate":289.66},"Child Mortality":{"# Deaths":16,"Child Mortality Rate":90.91},"Infant Mortality":{"# Deaths":"","Infant Mortality Rate":""},"Frequent Physical Distress":{"% Frequent Physical Distress":10.1},"Frequent Mental Distress":{"% Frequent Mental Distress":14.2},"Diabetes Prevalence":{"% Adults with Diabetes":8.7},"HIV Prevalence":{"# HIV Cases":"","HIV Prevalence Rate":""},"Food Insecurity":{"# Food Insecure":990,"% Food Insecure":7.2},"Limited Access to Healthy Foods":{"# Limited Access to Healthy Foods":166.83,"% Limited Access to Healthy Foods":1.3},"Drug Overdose Deaths":{"# Drug Overdose Deaths":"","Drug Overdose Mortality Rate":""},"Insufficient Sleep":{"% Insufficient Sleep":31.9},"Uninsured Adults":{"# Uninsured Adults":1199,"% Uninsured Adults":15.54},"Uninsured Children":{"# Uninsured Children":384,"% Uninsured Children":8.49},"Other Primary Care Providers":{"Other Primary Care Provider Rate":27.27,"Other Primary Care Provider Ratio":"3667:1"},"High School Graduation":{"Cohort Size":262,"High School Graduation Rate":86.76},"Disconnected Youth":{"% Disconnected Youth":""},"Reading Scores":{"Average Grade Performance":3.17},"Math Scores":{"Average Grade Performance":3.2},"School Segregation":{"Segregation Index":0.02},"School Funding Adequacy":{"Spending per Pupil":7005.5,"School Funding Adequacy":-82.63},"Gender Pay Gap":{"Women's Median Earnings":35682,"Men's Median Earnings":49823,"Gender Pay Gap":0.72},"Median Household Income":{"Median Household Income":59974},"Children Eligible for Free or Reduced Price Lunch":{"% Enrolled in Free or Reduced Lunch":28.76},"Residential Segregation - Black/White":{"Segregation Index":""},"Child Care Cost Burden":{"% Household Income Required for Child Care Expenses":21.7},"Child Care Centers":{"# Child Care Centers":1,"Child Care Centers per 1,000 Children":0.96},"Homicides":{"Homicide Rate":""},"Suicides":{"# Deaths":16,"Suicide Rate, Age-Adjusted":24.5,"Crude Rate":23.26},"Firearm Fatalities":{"# Firearm Fatalities":12,"Firearm Fatalities Rate":17.45},"Motor Vehicle Crash Deaths":{"# Motor Vehicle Deaths":21,"Motor Vehicle Mortality Rate":22.13},"Juvenile Arrests":{"Non-Petitioned Cases":"","Petitioned Cases":"","Denominator":"","Juvenile Arrest Rate":""},"Voter Turnout":{"% Voter Turnout":72.87},"Census Participation":{"% Census Participation":71.3},"Traffic Volume":{"Traffic Volume":57.62},"Homeownership":{"# Homeowners":3714,"% Homeowners":81.97},"Severe Housing Cost Burden":{"# Households with Severe Cost Burden":533,"% Households with Severe Cost Burden":11.96},"Broadband Access":{"% Households with Broadband Access":91.41,"# Households with Broadband Access":4142},"Population":{"Population":14666},"% Below 18 Years of Age":{"% Less than 18 Years of Age":30.9},"% 65 and Older":{"% 65 and Over":14.62},"% Non-Hispanic Black":{"# Black":52,"% Black":0.35},"% American Indian or Alaska Native":{"# American Indian or Alaska Native":160,"% American Indian or Alaska Native":1.09},"% Asian":{"# Asian":49,"% Asian":0.33},"% Native Hawaiian or Other Pacific Islander":{"# Native Hawaiian or Other Pacific Islander":13,"% Native Hawaiian or Other Pacific Islander":0.09},"% Hispanic":{"# Hispanic":1036,"% Hispanic":7.06},"% Non-Hispanic White":{"# Non-Hispanic White":13268,"% Non-Hispanic White":90.47},"% Not Proficient in English":{"# Not Proficient in English":59,"% Not Proficient in English":0.45},"% Female":{"% Female":48.47},"% Rural":{"# Rural Residents":8463,"% Rural":66.19}}