{"About":{"FIPS":"18133","State":"Indiana","Population":"","County":"Putnam"},"Premature Death":{"Unreliable":"","Deaths":509,"Years of Potential Life Lost Rate":7407.03},"Poor or Fair Health":{"% Fair or Poor Health":15.2},"Poor Physical Health Days":{"Average Number of Physically Unhealthy Days":3.54},"Poor Mental Health Days":{"Average Number of Mentally Unhealthy Days":4.92},"Low Birthweight":{"Unreliable":"","% Low Birthweight":6.72},"Adult Smoking":{"% Adults Reporting Currently Smoking":21.8},"Adult Obesity":{"% Adults with Obesity":38.6},"Food Environment Index":{"Food Environment Index":8.3},"Physical Inactivity":{"% Physically Inactive":27.6},"Access to Exercise Opportunities":{"% With Access to Exercise Opportunities":63.18},"Excessive Drinking":{"% Excessive Drinking":17.73},"Alcohol-Impaired Driving Deaths":{"# Alcohol-Impaired Driving Deaths":5,"# Driving Deaths":34,"% Driving Deaths with Alcohol Involvement":14.71},"Sexually Transmitted Infections":{"# Chlamydia Cases":100,"Chlamydia Rate":266.1},"Teen Births":{"Teen Birth Rate":15.86},"Uninsured":{"Number of Uninsured":2085,"Percent of Total Population Uninsured":7.9},"Primary Care Physicians":{"# Primary Care Physicians":12,"Primary Care Physicians Rate":32.03,"Primary Care Physicians Ratio":"3122:1"},"Dentists":{"# Dentists":17,"Dentist Rate":45.97,"Dentist Ratio":"2175:1"},"Mental Health Providers":{"# Mental Health Providers":36,"Mental Health Provider Rate":97.35,"Mental Health Provider Ratio":"1027:1"},"Preventable Hospital Stays":{"Preventable Hospitalization Rate":2617},"Mammography Screening":{"% with Annual Mammogram":36},"Flu Vaccinations":{"% Vaccinated":53},"High School Completion":{"# Completed High School":21866,"Population":24529,"% Completed High School":89.14},"Some College":{"# Some College":4306,"Population":8850,"% Some College":48.66},"Unemployment":{"# Unemployed":499,"Labor Force":16353,"% Unemployed":3.05},"Children in Poverty":{"% Children in Poverty":15.1},"Income Inequality":{"80th Percentile Income":111122,"20th Percentile Income":29674,"Income Ratio":3.74},"Children in Single-Parent Households":{"# Children in Single-Parent Households":1493,"# Children in Households":7224,"% Children in Single-Parent Households":20.67},"Social Associations":{"# Associations":47,"Social Association Rate":12.54},"Injury Deaths":{"# Injury Deaths":132,"Injury Death Rate":70.23},"Air Pollution - Particulate Matter":{"Average Daily PM2.5":9.1},"Drinking Water Violations":{"Presence of Water Violation":"No"},"Severe Housing Problems":{"% Severe Housing Problems":9.38,"Severe Housing Cost Burden":6.47,"Overcrowding":2.4,"Inadequate Facilities":0.7},"Driving Alone to Work":{"% Drive Alone to Work":78.83},"Long Commute - Driving Alone":{"# Workers who Drive Alone":15806,"% Long Commute - Drives Alone":40.8},"Life Expectancy":{"Life Expectancy":77.72},"Premature Age-Adjusted Mortality":{"# Deaths":509,"Age-Adjusted Death Rate":382.08},"Child Mortality":{"# Deaths":13,"Child Mortality Rate":44.37},"Infant Mortality":{"# Deaths":"","Infant Mortality Rate":""},"Frequent Physical Distress":{"% Frequent Physical Distress":10.7},"Frequent Mental Distress":{"% Frequent Mental Distress":16.1},"Diabetes Prevalence":{"% Adults with Diabetes":10.1},"HIV Prevalence":{"# HIV Cases":57,"HIV Prevalence Rate":176},"Food Insecurity":{"# Food Insecure":3960,"% Food Insecure":10.6},"Limited Access to Healthy Foods":{"# Limited Access to Healthy Foods":1343.56,"% Limited Access to Healthy Foods":3.54},"Drug Overdose Deaths":{"# Drug Overdose Deaths":17,"Drug Overdose Mortality Rate":15.07},"Insufficient Sleep":{"% Insufficient Sleep":34.3},"Uninsured Adults":{"# Uninsured Adults":1702,"% Uninsured Adults":8.79},"Uninsured Children":{"# Uninsured Children":417,"% Uninsured Children":5.65},"Other Primary Care Providers":{"Other Primary Care Provider Rate":70.31,"Other Primary Care Provider Ratio":"1422:1"},"High School Graduation":{"Cohort Size":412,"High School Graduation Rate":94.78},"Disconnected Youth":{"% Disconnected Youth":""},"Reading Scores":{"Average Grade Performance":3.29},"Math Scores":{"Average Grade Performance":3.51},"School Segregation":{"Segregation Index":0.05},"School Funding Adequacy":{"Spending per Pupil":10229.5,"School Funding Adequacy":-720.88},"Gender Pay Gap":{"Women's Median Earnings":37709,"Men's Median Earnings":50902,"Gender Pay Gap":0.74},"Median Household Income":{"Median Household Income":61223},"Children Eligible for Free or Reduced Price Lunch":{"% Enrolled in Free or Reduced Lunch":48.23},"Residential Segregation - Black/White":{"Segregation Index":73.13},"Child Care Cost Burden":{"% Household Income Required for Child Care Expenses":19.15},"Child Care Centers":{"# Child Care Centers":4,"Child Care Centers per 1,000 Children":2.23},"Homicides":{"Homicide Rate":""},"Suicides":{"# Deaths":43,"Suicide Rate, Age-Adjusted":21.74,"Crude Rate":22.88},"Firearm Fatalities":{"# Firearm Fatalities":29,"Firearm Fatalities Rate":15.43},"Motor Vehicle Crash Deaths":{"# Motor Vehicle Deaths":41,"Motor Vehicle Mortality Rate":15.58},"Juvenile Arrests":{"Non-Petitioned Cases":"1-4","Petitioned Cases":68,"Denominator":3400,"Juvenile Arrest Rate":""},"Voter Turnout":{"% Voter Turnout":56.25},"Census Participation":{"% Census Participation":65.8},"Traffic Volume":{"Traffic Volume":216.03},"Homeownership":{"# Homeowners":9899,"% Homeowners":73.47},"Severe Housing Cost Burden":{"# Households with Severe Cost Burden":722,"% Households with Severe Cost Burden":5.49},"Broadband Access":{"% Households with Broadband Access":83.88,"# Households with Broadband Access":11302},"Population":{"Population":36979},"% Below 18 Years of Age":{"% Less than 18 Years of Age":19.5},"% 65 and Older":{"% 65 and Over":16.83},"% Non-Hispanic Black":{"# Black":1423,"% Black":3.85},"% American Indian or Alaska Native":{"# American Indian or Alaska Native":141,"% American Indian or Alaska Native":0.38},"% Asian":{"# Asian":459,"% Asian":1.24},"% Native Hawaiian or Other Pacific Islander":{"# Native Hawaiian or Other Pacific Islander":19,"% Native Hawaiian or Other Pacific Islander":0.05},"% Hispanic":{"# Hispanic":774,"% Hispanic":2.09},"% Non-Hispanic White":{"# Non-Hispanic White":33675,"% Non-Hispanic White":91.07},"% Not Proficient in English":{"# Not Proficient in English":189,"% Not Proficient in English":0.54},"% Female":{"% Female":46.76},"% Rural":{"# Rural Residents":24601,"% Rural":64.8}}