{"About":{"FIPS":"24033","State":"Maryland","Population":"","County":"Prince George's"},"Premature Death":{"Unreliable":"","Deaths":11369,"Years of Potential Life Lost Rate":7484.45},"Poor or Fair Health":{"% Fair or Poor Health":13.8},"Poor Physical Health Days":{"Average Number of Physically Unhealthy Days":2.67},"Poor Mental Health Days":{"Average Number of Mentally Unhealthy Days":4.01},"Low Birthweight":{"Unreliable":"","% Low Birthweight":9.45},"Adult Smoking":{"% Adults Reporting Currently Smoking":11.6},"Adult Obesity":{"% Adults with Obesity":36.9},"Food Environment Index":{"Food Environment Index":8.8},"Physical Inactivity":{"% Physically Inactive":23.4},"Access to Exercise Opportunities":{"% With Access to Exercise Opportunities":97.32},"Excessive Drinking":{"% Excessive Drinking":12.11},"Alcohol-Impaired Driving Deaths":{"# Alcohol-Impaired Driving Deaths":151,"# Driving Deaths":488,"% Driving Deaths with Alcohol Involvement":30.94},"Sexually Transmitted Infections":{"# Chlamydia Cases":6974,"Chlamydia Rate":766.9},"Teen Births":{"Teen Birth Rate":19.56},"Uninsured":{"Number of Uninsured":82832,"Percent of Total Population Uninsured":11.19},"Primary Care Physicians":{"# Primary Care Physicians":473,"Primary Care Physicians Rate":52,"Primary Care Physicians Ratio":"1923:1"},"Dentists":{"# Dentists":591,"Dentist Rate":61.86,"Dentist Ratio":"1616:1"},"Mental Health Providers":{"# Mental Health Providers":1836,"Mental Health Provider Rate":192.19,"Mental Health Provider Ratio":"520:1"},"Preventable Hospital Stays":{"Preventable Hospitalization Rate":3021},"Mammography Screening":{"% with Annual Mammogram":34},"Flu Vaccinations":{"% Vaccinated":44},"High School Completion":{"# Completed High School":569766,"Population":653179,"% Completed High School":87.23},"Some College":{"# Some College":169240,"Population":266660,"% Some College":63.47},"Unemployment":{"# Unemployed":37514,"Labor Force":502972,"% Unemployed":7.46},"Children in Poverty":{"% Children in Poverty":15.7},"Income Inequality":{"80th Percentile Income":164339,"20th Percentile Income":42329,"Income Ratio":3.88},"Children in Single-Parent Households":{"# Children in Single-Parent Households":70400,"# Children in Households":213467,"% Children in Single-Parent Households":32.98},"Social Associations":{"# Associations":724,"Social Association Rate":7.96},"Injury Deaths":{"# Injury Deaths":2806,"Injury Death Rate":61.68},"Air Pollution - Particulate Matter":{"Average Daily PM2.5":7.2},"Drinking Water Violations":{"Presence of Water Violation":"No"},"Severe Housing Problems":{"% Severe Housing Problems":19.07,"Severe Housing Cost Burden":15.34,"Overcrowding":3.96,"Inadequate Facilities":0.67},"Driving Alone to Work":{"% Drive Alone to Work":64.27},"Long Commute - Driving Alone":{"# Workers who Drive Alone":494767,"% Long Commute - Drives Alone":61.1},"Life Expectancy":{"Life Expectancy":78.51},"Premature Age-Adjusted Mortality":{"# Deaths":11369,"Age-Adjusted Death Rate":364.73},"Child Mortality":{"# Deaths":458,"Child Mortality Rate":56.71},"Infant Mortality":{"# Deaths":620,"Infant Mortality Rate":7.46},"Frequent Physical Distress":{"% Frequent Physical Distress":8.1},"Frequent Mental Distress":{"% Frequent Mental Distress":13},"Diabetes Prevalence":{"% Adults with Diabetes":12.5},"HIV Prevalence":{"# HIV Cases":8064,"HIV Prevalence Rate":1058.4},"Food Insecurity":{"# Food Insecure":74130,"% Food Insecure":8.1},"Limited Access to Healthy Foods":{"# Limited Access to Healthy Foods":29866.96,"% Limited Access to Healthy Foods":3.46},"Drug Overdose Deaths":{"# Drug Overdose Deaths":528,"Drug Overdose Mortality Rate":19.35},"Insufficient Sleep":{"% Insufficient Sleep":40.8},"Uninsured Adults":{"# Uninsured Adults":73503,"% Uninsured Adults":13.36},"Uninsured Children":{"# Uninsured Children":10052,"% Uninsured Children":5.04},"Other Primary Care Providers":{"Other Primary Care Provider Rate":78.82,"Other Primary Care Provider Ratio":"1269:1"},"High School Graduation":{"Cohort Size":10462,"High School Graduation Rate":76},"Disconnected Youth":{"% Disconnected Youth":6.21},"Reading Scores":{"Average Grade Performance":""},"Math Scores":{"Average Grade Performance":""},"School Segregation":{"Segregation Index":0.2},"School Funding Adequacy":{"Spending per Pupil":15913,"School Funding Adequacy":-4503.91},"Gender Pay Gap":{"Women's Median Earnings":62568,"Men's Median Earnings":57276,"Gender Pay Gap":1.09},"Median Household Income":{"Median Household Income":89689},"Children Eligible for Free or Reduced Price Lunch":{"% Enrolled in Free or Reduced Lunch":66.49},"Residential Segregation - Black/White":{"Segregation Index":47.83},"Child Care Cost Burden":{"% Household Income Required for Child Care Expenses":25.05},"Child Care Centers":{"# Child Care Centers":275,"Child Care Centers per 1,000 Children":4.48},"Homicides":{"Homicide Rate":10.91},"Suicides":{"# Deaths":295,"Suicide Rate, Age-Adjusted":6.32,"Crude Rate":6.48},"Firearm Fatalities":{"# Firearm Fatalities":532,"Firearm Fatalities Rate":11.69},"Motor Vehicle Crash Deaths":{"# Motor Vehicle Deaths":647,"Motor Vehicle Mortality Rate":10.17},"Juvenile Arrests":{"Non-Petitioned Cases":682,"Petitioned Cases":431,"Denominator":85700,"Juvenile Arrest Rate":12.99},"Voter Turnout":{"% Voter Turnout":70.67},"Census Participation":{"% Census Participation":67.9},"Traffic Volume":{"Traffic Volume":825.37},"Homeownership":{"# Homeowners":209794,"% Homeowners":62.19},"Severe Housing Cost Burden":{"# Households with Severe Cost Burden":54008,"% Households with Severe Cost Burden":16.29},"Broadband Access":{"% Households with Broadband Access":91.11,"# Households with Broadband Access":307362},"Population":{"Population":955306},"% Below 18 Years of Age":{"% Less than 18 Years of Age":22.08},"% 65 and Older":{"% 65 and Over":14.51},"% Non-Hispanic Black":{"# Black":585444,"% Black":61.28},"% American Indian or Alaska Native":{"# American Indian or Alaska Native":12525,"% American Indian or Alaska Native":1.31},"% Asian":{"# Asian":41961,"% Asian":4.39},"% Native Hawaiian or Other Pacific Islander":{"# Native Hawaiian or Other Pacific Islander":2200,"% Native Hawaiian or Other Pacific Islander":0.23},"% Hispanic":{"# Hispanic":194431,"% Hispanic":20.35},"% Non-Hispanic White":{"# Non-Hispanic White":113215,"% Non-Hispanic White":11.85},"% Not Proficient in English":{"# Not Proficient in English":64087,"% Not Proficient in English":7.15},"% Female":{"% Female":51.72},"% Rural":{"# Rural Residents":16981,"% Rural":1.97}}