{"About":{"FIPS":"27059","State":"Minnesota","Population":"","County":"Isanti"},"Premature Death":{"Unreliable":"","Deaths":434,"Years of Potential Life Lost Rate":6310.68},"Poor or Fair Health":{"% Fair or Poor Health":11.1},"Poor Physical Health Days":{"Average Number of Physically Unhealthy Days":2.92},"Poor Mental Health Days":{"Average Number of Mentally Unhealthy Days":4.47},"Low Birthweight":{"Unreliable":"","% Low Birthweight":6.12},"Adult Smoking":{"% Adults Reporting Currently Smoking":19},"Adult Obesity":{"% Adults with Obesity":34.4},"Food Environment Index":{"Food Environment Index":8.6},"Physical Inactivity":{"% Physically Inactive":20.4},"Access to Exercise Opportunities":{"% With Access to Exercise Opportunities":42.3},"Excessive Drinking":{"% Excessive Drinking":22.42},"Alcohol-Impaired Driving Deaths":{"# Alcohol-Impaired Driving Deaths":7,"# Driving Deaths":31,"% Driving Deaths with Alcohol Involvement":22.58},"Sexually Transmitted Infections":{"# Chlamydia Cases":76,"Chlamydia Rate":187.2},"Teen Births":{"Teen Birth Rate":10.28},"Uninsured":{"Number of Uninsured":1981,"Percent of Total Population Uninsured":5.77},"Primary Care Physicians":{"# Primary Care Physicians":26,"Primary Care Physicians Rate":62.76,"Primary Care Physicians Ratio":"1593:1"},"Dentists":{"# Dentists":21,"Dentist Rate":50.11,"Dentist Ratio":"1996:1"},"Mental Health Providers":{"# Mental Health Providers":81,"Mental Health Provider Rate":193.29,"Mental Health Provider Ratio":"517:1"},"Preventable Hospital Stays":{"Preventable Hospitalization Rate":2088},"Mammography Screening":{"% with Annual Mammogram":41},"Flu Vaccinations":{"% Vaccinated":57},"High School Completion":{"# Completed High School":25812,"Population":28068,"% Completed High School":91.96},"Some College":{"# Some College":6544,"Population":10236,"% Some College":63.93},"Unemployment":{"# Unemployed":868,"Labor Force":21344,"% Unemployed":4.07},"Children in Poverty":{"% Children in Poverty":9.4},"Income Inequality":{"80th Percentile Income":132078,"20th Percentile Income":36207,"Income Ratio":3.65},"Children in Single-Parent Households":{"# Children in Single-Parent Households":1755,"# Children in Households":9596,"% Children in Single-Parent Households":18.29},"Social Associations":{"# Associations":42,"Social Association Rate":10.14},"Injury Deaths":{"# Injury Deaths":154,"Injury Death Rate":76.77},"Air Pollution - Particulate Matter":{"Average Daily PM2.5":6.2},"Drinking Water Violations":{"Presence of Water Violation":"No"},"Severe Housing Problems":{"% Severe Housing Problems":10.77,"Severe Housing Cost Burden":8.92,"Overcrowding":1.64,"Inadequate Facilities":0.5},"Driving Alone to Work":{"% Drive Alone to Work":82.72},"Long Commute - Driving Alone":{"# Workers who Drive Alone":20189,"% Long Commute - Drives Alone":53.6},"Life Expectancy":{"Life Expectancy":79.56},"Premature Age-Adjusted Mortality":{"# Deaths":434,"Age-Adjusted Death Rate":301.44},"Child Mortality":{"# Deaths":18,"Child Mortality Rate":47.23},"Infant Mortality":{"# Deaths":21,"Infant Mortality Rate":6.79},"Frequent Physical Distress":{"% Frequent Physical Distress":9},"Frequent Mental Distress":{"% Frequent Mental Distress":14.5},"Diabetes Prevalence":{"% Adults with Diabetes":7.9},"HIV Prevalence":{"# HIV Cases":16,"HIV Prevalence Rate":46.3},"Food Insecurity":{"# Food Insecure":2810,"% Food Insecure":7},"Limited Access to Healthy Foods":{"# Limited Access to Healthy Foods":2934.96,"% Limited Access to Healthy Foods":7.76},"Drug Overdose Deaths":{"# Drug Overdose Deaths":18,"Drug Overdose Mortality Rate":14.76},"Insufficient Sleep":{"% Insufficient Sleep":31.3},"Uninsured Adults":{"# Uninsured Adults":1628,"% Uninsured Adults":6.58},"Uninsured Children":{"# Uninsured Children":381,"% Uninsured Children":3.8},"Other Primary Care Providers":{"Other Primary Care Provider Rate":26.25,"Other Primary Care Provider Ratio":"3810:1"},"High School Graduation":{"Cohort Size":447,"High School Graduation Rate":86.11},"Disconnected Youth":{"% Disconnected Youth":""},"Reading Scores":{"Average Grade Performance":3.08},"Math Scores":{"Average Grade Performance":3.38},"School Segregation":{"Segregation Index":0.02},"School Funding Adequacy":{"Spending per Pupil":10584.5,"School Funding Adequacy":1521.02},"Gender Pay Gap":{"Women's Median Earnings":47714,"Men's Median Earnings":61996,"Gender Pay Gap":0.77},"Median Household Income":{"Median Household Income":74481},"Children Eligible for Free or Reduced Price Lunch":{"% Enrolled in Free or Reduced Lunch":25.18},"Residential Segregation - Black/White":{"Segregation Index":64.95},"Child Care Cost Burden":{"% Household Income Required for Child Care Expenses":23.91},"Child Care Centers":{"# Child Care Centers":15,"Child Care Centers per 1,000 Children":6.28},"Homicides":{"Homicide Rate":""},"Suicides":{"# Deaths":34,"Suicide Rate, Age-Adjusted":16.92,"Crude Rate":16.95},"Firearm Fatalities":{"# Firearm Fatalities":17,"Firearm Fatalities Rate":8.47},"Motor Vehicle Crash Deaths":{"# Motor Vehicle Deaths":36,"Motor Vehicle Mortality Rate":12.98},"Juvenile Arrests":{"Non-Petitioned Cases":"","Petitioned Cases":75,"Denominator":4500,"Juvenile Arrest Rate":16.67},"Voter Turnout":{"% Voter Turnout":80.34},"Census Participation":{"% Census Participation":78.2},"Traffic Volume":{"Traffic Volume":67},"Homeownership":{"# Homeowners":12883,"% Homeowners":84.21},"Severe Housing Cost Burden":{"# Households with Severe Cost Burden":1641,"% Households with Severe Cost Burden":10.92},"Broadband Access":{"% Households with Broadband Access":87.91,"# Households with Broadband Access":13449},"Population":{"Population":41906},"% Below 18 Years of Age":{"% Less than 18 Years of Age":23.3},"% 65 and Older":{"% 65 and Over":16.79},"% Non-Hispanic Black":{"# Black":419,"% Black":1},"% American Indian or Alaska Native":{"# American Indian or Alaska Native":343,"% American Indian or Alaska Native":0.82},"% Asian":{"# Asian":633,"% Asian":1.51},"% Native Hawaiian or Other Pacific Islander":{"# Native Hawaiian or Other Pacific Islander":29,"% Native Hawaiian or Other Pacific Islander":0.07},"% Hispanic":{"# Hispanic":1031,"% Hispanic":2.46},"% Non-Hispanic White":{"# Non-Hispanic White":38674,"% Non-Hispanic White":92.29},"% Not Proficient in English":{"# Not Proficient in English":105,"% Not Proficient in English":0.27},"% Female":{"% Female":49.25},"% Rural":{"# Rural Residents":23546,"% Rural":62.26}}