{"About":{"FIPS":"28081","State":"Mississippi","Population":"","County":"Lee"},"Premature Death":{"Unreliable":"","Deaths":1456,"Years of Potential Life Lost Rate":10547.42},"Poor or Fair Health":{"% Fair or Poor Health":16.8},"Poor Physical Health Days":{"Average Number of Physically Unhealthy Days":3},"Poor Mental Health Days":{"Average Number of Mentally Unhealthy Days":4.05},"Low Birthweight":{"Unreliable":"","% Low Birthweight":12.5},"Adult Smoking":{"% Adults Reporting Currently Smoking":17.7},"Adult Obesity":{"% Adults with Obesity":38.6},"Food Environment Index":{"Food Environment Index":7.1},"Physical Inactivity":{"% Physically Inactive":26.5},"Access to Exercise Opportunities":{"% With Access to Exercise Opportunities":51.85},"Excessive Drinking":{"% Excessive Drinking":14.89},"Alcohol-Impaired Driving Deaths":{"# Alcohol-Impaired Driving Deaths":12,"# Driving Deaths":96,"% Driving Deaths with Alcohol Involvement":12.5},"Sexually Transmitted Infections":{"# Chlamydia Cases":697,"Chlamydia Rate":815.8},"Teen Births":{"Teen Birth Rate":36.02},"Uninsured":{"Number of Uninsured":9698,"Percent of Total Population Uninsured":13.75},"Primary Care Physicians":{"# Primary Care Physicians":93,"Primary Care Physicians Rate":108.82,"Primary Care Physicians Ratio":"919:1"},"Dentists":{"# Dentists":61,"Dentist Rate":73.6,"Dentist Ratio":"1359:1"},"Mental Health Providers":{"# Mental Health Providers":604,"Mental Health Provider Rate":728.74,"Mental Health Provider Ratio":"137:1"},"Preventable Hospital Stays":{"Preventable Hospitalization Rate":2962},"Mammography Screening":{"% with Annual Mammogram":40},"Flu Vaccinations":{"% Vaccinated":56},"High School Completion":{"# Completed High School":47869,"Population":55501,"% Completed High School":86.25},"Some College":{"# Some College":15074,"Population":21963,"% Some College":68.63},"Unemployment":{"# Unemployed":1902,"Labor Force":41213,"% Unemployed":4.62},"Children in Poverty":{"% Children in Poverty":21.5},"Income Inequality":{"80th Percentile Income":112643,"20th Percentile Income":23310,"Income Ratio":4.83},"Children in Single-Parent Households":{"# Children in Single-Parent Households":6167,"# Children in Households":21081,"% Children in Single-Parent Households":29.25},"Social Associations":{"# Associations":109,"Social Association Rate":12.75},"Injury Deaths":{"# Injury Deaths":408,"Injury Death Rate":95.68},"Air Pollution - Particulate Matter":{"Average Daily PM2.5":9.6},"Drinking Water Violations":{"Presence of Water Violation":"No"},"Severe Housing Problems":{"% Severe Housing Problems":15.28,"Severe Housing Cost Burden":11.54,"Overcrowding":4.5,"Inadequate Facilities":0.92},"Driving Alone to Work":{"% Drive Alone to Work":88.3},"Long Commute - Driving Alone":{"# Workers who Drive Alone":38169,"% Long Commute - Drives Alone":21},"Life Expectancy":{"Life Expectancy":74.07},"Premature Age-Adjusted Mortality":{"# Deaths":1456,"Age-Adjusted Death Rate":504.63},"Child Mortality":{"# Deaths":66,"Child Mortality Rate":76.93},"Infant Mortality":{"# Deaths":81,"Infant Mortality Rate":10.3},"Frequent Physical Distress":{"% Frequent Physical Distress":9.7},"Frequent Mental Distress":{"% Frequent Mental Distress":14.4},"Diabetes Prevalence":{"% Adults with Diabetes":10.7},"HIV Prevalence":{"# HIV Cases":212,"HIV Prevalence Rate":301.2},"Food Insecurity":{"# Food Insecure":12650,"% Food Insecure":14.8},"Limited Access to Healthy Foods":{"# Limited Access to Healthy Foods":5714.2,"% Limited Access to Healthy Foods":6.89},"Drug Overdose Deaths":{"# Drug Overdose Deaths":37,"Drug Overdose Mortality Rate":14.45},"Insufficient Sleep":{"% Insufficient Sleep":31.9},"Uninsured Adults":{"# Uninsured Adults":8627,"% Uninsured Adults":17.28},"Uninsured Children":{"# Uninsured Children":1185,"% Uninsured Children":5.49},"Other Primary Care Providers":{"Other Primary Care Provider Rate":341.45,"Other Primary Care Provider Ratio":"293:1"},"High School Graduation":{"Cohort Size":1163,"High School Graduation Rate":87.93},"Disconnected Youth":{"% Disconnected Youth":""},"Reading Scores":{"Average Grade Performance":3.11},"Math Scores":{"Average Grade Performance":3.23},"School Segregation":{"Segregation Index":0.14},"School Funding Adequacy":{"Spending per Pupil":9724.25,"School Funding Adequacy":-4271.14},"Gender Pay Gap":{"Women's Median Earnings":37591,"Men's Median Earnings":52484,"Gender Pay Gap":0.72},"Median Household Income":{"Median Household Income":57597},"Children Eligible for Free or Reduced Price Lunch":{"% Enrolled in Free or Reduced Lunch":99.46},"Residential Segregation - Black/White":{"Segregation Index":43.4},"Child Care Cost Burden":{"% Household Income Required for Child Care Expenses":17.25},"Child Care Centers":{"# Child Care Centers":68,"Child Care Centers per 1,000 Children":12.34},"Homicides":{"Homicide Rate":10.05},"Suicides":{"# Deaths":57,"Suicide Rate, Age-Adjusted":13.72,"Crude Rate":13.37},"Firearm Fatalities":{"# Firearm Fatalities":88,"Firearm Fatalities Rate":20.64},"Motor Vehicle Crash Deaths":{"# Motor Vehicle Deaths":141,"Motor Vehicle Mortality Rate":23.62},"Juvenile Arrests":{"Non-Petitioned Cases":214,"Petitioned Cases":126,"Denominator":9800,"Juvenile Arrest Rate":34.69},"Voter Turnout":{"% Voter Turnout":58.98},"Census Participation":{"% Census Participation":63.3},"Traffic Volume":{"Traffic Volume":108.87},"Homeownership":{"# Homeowners":22192,"% Homeowners":70.06},"Severe Housing Cost Burden":{"# Households with Severe Cost Burden":3390,"% Households with Severe Cost Burden":11.15},"Broadband Access":{"% Households with Broadband Access":78.78,"# Households with Broadband Access":24954},"Population":{"Population":82883},"% Below 18 Years of Age":{"% Less than 18 Years of Age":25.07},"% 65 and Older":{"% 65 and Over":15.35},"% Non-Hispanic Black":{"# Black":25532,"% Black":30.8},"% American Indian or Alaska Native":{"# American Indian or Alaska Native":328,"% American Indian or Alaska Native":0.4},"% Asian":{"# Asian":834,"% Asian":1.01},"% Native Hawaiian or Other Pacific Islander":{"# Native Hawaiian or Other Pacific Islander":28,"% Native Hawaiian or Other Pacific Islander":0.03},"% Hispanic":{"# Hispanic":2632,"% Hispanic":3.18},"% Non-Hispanic White":{"# Non-Hispanic White":52587,"% Non-Hispanic White":63.45},"% Not Proficient in English":{"# Not Proficient in English":711,"% Not Proficient in English":0.91},"% Female":{"% Female":52.01},"% Rural":{"# Rural Residents":37612,"% Rural":45.36}}