{"About":{"FIPS":"44005","State":"Rhode Island","Population":"","County":"Newport"},"Premature Death":{"Unreliable":"","Deaths":845,"Years of Potential Life Lost Rate":4939.34},"Poor or Fair Health":{"% Fair or Poor Health":9.3},"Poor Physical Health Days":{"Average Number of Physically Unhealthy Days":2.58},"Poor Mental Health Days":{"Average Number of Mentally Unhealthy Days":4.39},"Low Birthweight":{"Unreliable":"","% Low Birthweight":6.83},"Adult Smoking":{"% Adults Reporting Currently Smoking":12.8},"Adult Obesity":{"% Adults with Obesity":24.9},"Food Environment Index":{"Food Environment Index":8.6},"Physical Inactivity":{"% Physically Inactive":15.4},"Access to Exercise Opportunities":{"% With Access to Exercise Opportunities":92.91},"Excessive Drinking":{"% Excessive Drinking":23.1},"Alcohol-Impaired Driving Deaths":{"# Alcohol-Impaired Driving Deaths":4,"# Driving Deaths":17,"% Driving Deaths with Alcohol Involvement":23.53},"Sexually Transmitted Infections":{"# Chlamydia Cases":178,"Chlamydia Rate":216.9},"Teen Births":{"Teen Birth Rate":7.05},"Uninsured":{"Number of Uninsured":2271,"Percent of Total Population Uninsured":3.81},"Primary Care Physicians":{"# Primary Care Physicians":71,"Primary Care Physicians Rate":86.76,"Primary Care Physicians Ratio":"1153:1"},"Dentists":{"# Dentists":85,"Dentist Rate":99.69,"Dentist Ratio":"1003:1"},"Mental Health Providers":{"# Mental Health Providers":317,"Mental Health Provider Rate":371.79,"Mental Health Provider Ratio":"269:1"},"Preventable Hospital Stays":{"Preventable Hospitalization Rate":2168},"Mammography Screening":{"% with Annual Mammogram":48},"Flu Vaccinations":{"% Vaccinated":50},"High School Completion":{"# Completed High School":59828,"Population":63375,"% Completed High School":94.4},"Some College":{"# Some College":15298,"Population":19985,"% Some College":76.55},"Unemployment":{"# Unemployed":2215,"Labor Force":45042,"% Unemployed":4.92},"Children in Poverty":{"% Children in Poverty":12.7},"Income Inequality":{"80th Percentile Income":166026,"20th Percentile Income":35776,"Income Ratio":4.64},"Children in Single-Parent Households":{"# Children in Single-Parent Households":3069,"# Children in Households":14192,"% Children in Single-Parent Households":21.62},"Social Associations":{"# Associations":101,"Social Association Rate":12.34},"Injury Deaths":{"# Injury Deaths":307,"Injury Death Rate":74.39},"Air Pollution - Particulate Matter":{"Average Daily PM2.5":5.9},"Drinking Water Violations":{"Presence of Water Violation":"No"},"Severe Housing Problems":{"% Severe Housing Problems":15.41,"Severe Housing Cost Burden":14.1,"Overcrowding":0.85,"Inadequate Facilities":1.09},"Driving Alone to Work":{"% Drive Alone to Work":75.57},"Long Commute - Driving Alone":{"# Workers who Drive Alone":44730,"% Long Commute - Drives Alone":32.6},"Life Expectancy":{"Life Expectancy":82.02},"Premature Age-Adjusted Mortality":{"# Deaths":845,"Age-Adjusted Death Rate":247.12},"Child Mortality":{"# Deaths":21,"Child Mortality Rate":37.87},"Infant Mortality":{"# Deaths":22,"Infant Mortality Rate":4.45},"Frequent Physical Distress":{"% Frequent Physical Distress":8},"Frequent Mental Distress":{"% Frequent Mental Distress":13.8},"Diabetes Prevalence":{"% Adults with Diabetes":7.2},"HIV Prevalence":{"# HIV Cases":58,"HIV Prevalence Rate":80.1},"Food Insecurity":{"# Food Insecure":6940,"% Food Insecure":8.4},"Limited Access to Healthy Foods":{"# Limited Access to Healthy Foods":3849.8,"% Limited Access to Healthy Foods":4.64},"Drug Overdose Deaths":{"# Drug Overdose Deaths":63,"Drug Overdose Mortality Rate":25.56},"Insufficient Sleep":{"% Insufficient Sleep":30.3},"Uninsured Adults":{"# Uninsured Adults":1915,"% Uninsured Adults":4.15},"Uninsured Children":{"# Uninsured Children":394,"% Uninsured Children":2.78},"Other Primary Care Providers":{"Other Primary Care Provider Rate":79.75,"Other Primary Care Provider Ratio":"1254:1"},"High School Graduation":{"Cohort Size":749,"High School Graduation Rate":83.09},"Disconnected Youth":{"% Disconnected Youth":""},"Reading Scores":{"Average Grade Performance":3.16},"Math Scores":{"Average Grade Performance":3.2},"School Segregation":{"Segregation Index":0.13},"School Funding Adequacy":{"Spending per Pupil":19763.83,"School Funding Adequacy":9658.33},"Gender Pay Gap":{"Women's Median Earnings":57787,"Men's Median Earnings":71225,"Gender Pay Gap":0.81},"Median Household Income":{"Median Household Income":85764},"Children Eligible for Free or Reduced Price Lunch":{"% Enrolled in Free or Reduced Lunch":31.25},"Residential Segregation - Black/White":{"Segregation Index":60.07},"Child Care Cost Burden":{"% Household Income Required for Child Care Expenses":22.81},"Child Care Centers":{"# Child Care Centers":40,"Child Care Centers per 1,000 Children":10.99},"Homicides":{"Homicide Rate":""},"Suicides":{"# Deaths":51,"Suicide Rate, Age-Adjusted":11.15,"Crude Rate":12.36},"Firearm Fatalities":{"# Firearm Fatalities":16,"Firearm Fatalities Rate":3.88},"Motor Vehicle Crash Deaths":{"# Motor Vehicle Deaths":29,"Motor Vehicle Mortality Rate":5.02},"Juvenile Arrests":{"Non-Petitioned Cases":25,"Petitioned Cases":82,"Denominator":6400,"Juvenile Arrest Rate":16.72},"Voter Turnout":{"% Voter Turnout":69.11},"Census Participation":{"% Census Participation":65.2},"Traffic Volume":{"Traffic Volume":391.9},"Homeownership":{"# Homeowners":23147,"% Homeowners":65.52},"Severe Housing Cost Burden":{"# Households with Severe Cost Burden":5123,"% Households with Severe Cost Burden":14.94},"Broadband Access":{"% Households with Broadband Access":90.46,"# Households with Broadband Access":31959},"Population":{"Population":85264},"% Below 18 Years of Age":{"% Less than 18 Years of Age":16.21},"% 65 and Older":{"% 65 and Over":23.63},"% Non-Hispanic Black":{"# Black":3120,"% Black":3.66},"% American Indian or Alaska Native":{"# American Indian or Alaska Native":550,"% American Indian or Alaska Native":0.65},"% Asian":{"# Asian":1770,"% Asian":2.08},"% Native Hawaiian or Other Pacific Islander":{"# Native Hawaiian or Other Pacific Islander":106,"% Native Hawaiian or Other Pacific Islander":0.12},"% Hispanic":{"# Hispanic":5298,"% Hispanic":6.21},"% Non-Hispanic White":{"# Non-Hispanic White":72600,"% Non-Hispanic White":85.15},"% Not Proficient in English":{"# Not Proficient in English":930,"% Not Proficient in English":1.14},"% Female":{"% Female":50.22},"% Rural":{"# Rural Residents":10023,"% Rural":12.09}}