{"About":{"FIPS":"48373","State":"Texas","Population":"","County":"Polk"},"Premature Death":{"Unreliable":"","Deaths":1164,"Years of Potential Life Lost Rate":10901.28},"Poor or Fair Health":{"% Fair or Poor Health":21},"Poor Physical Health Days":{"Average Number of Physically Unhealthy Days":4.37},"Poor Mental Health Days":{"Average Number of Mentally Unhealthy Days":5.11},"Low Birthweight":{"Unreliable":"","% Low Birthweight":7.98},"Adult Smoking":{"% Adults Reporting Currently Smoking":24.5},"Adult Obesity":{"% Adults with Obesity":38.4},"Food Environment Index":{"Food Environment Index":6.6},"Physical Inactivity":{"% Physically Inactive":31.5},"Access to Exercise Opportunities":{"% With Access to Exercise Opportunities":29.23},"Excessive Drinking":{"% Excessive Drinking":20.63},"Alcohol-Impaired Driving Deaths":{"# Alcohol-Impaired Driving Deaths":15,"# Driving Deaths":74,"% Driving Deaths with Alcohol Involvement":20.27},"Sexually Transmitted Infections":{"# Chlamydia Cases":108,"Chlamydia Rate":210.3},"Teen Births":{"Teen Birth Rate":45.19},"Uninsured":{"Number of Uninsured":7722,"Percent of Total Population Uninsured":20},"Primary Care Physicians":{"# Primary Care Physicians":27,"Primary Care Physicians Rate":50.95,"Primary Care Physicians Ratio":"1963:1"},"Dentists":{"# Dentists":25,"Dentist Rate":48.17,"Dentist Ratio":"2076:1"},"Mental Health Providers":{"# Mental Health Providers":27,"Mental Health Provider Rate":52.02,"Mental Health Provider Ratio":"1922:1"},"Preventable Hospital Stays":{"Preventable Hospitalization Rate":2292},"Mammography Screening":{"% with Annual Mammogram":33},"Flu Vaccinations":{"% Vaccinated":48},"High School Completion":{"# Completed High School":28681,"Population":35680,"% Completed High School":80.38},"Some College":{"# Some College":4780,"Population":11734,"% Some College":40.74},"Unemployment":{"# Unemployed":1492,"Labor Force":18571,"% Unemployed":8.03},"Children in Poverty":{"% Children in Poverty":24.7},"Income Inequality":{"80th Percentile Income":103394,"20th Percentile Income":22417,"Income Ratio":4.61},"Children in Single-Parent Households":{"# Children in Single-Parent Households":3271,"# Children in Households":10020,"% Children in Single-Parent Households":32.64},"Social Associations":{"# Associations":38,"Social Association Rate":7.17},"Injury Deaths":{"# Injury Deaths":291,"Injury Death Rate":115.73},"Air Pollution - Particulate Matter":{"Average Daily PM2.5":9.2},"Drinking Water Violations":{"Presence of Water Violation":"Yes"},"Severe Housing Problems":{"% Severe Housing Problems":14.64,"Severe Housing Cost Burden":10.14,"Overcrowding":3.96,"Inadequate Facilities":1.19},"Driving Alone to Work":{"% Drive Alone to Work":83.74},"Long Commute - Driving Alone":{"# Workers who Drive Alone":17555,"% Long Commute - Drives Alone":33.6},"Life Expectancy":{"Life Expectancy":72.49},"Premature Age-Adjusted Mortality":{"# Deaths":1164,"Age-Adjusted Death Rate":522.64},"Child Mortality":{"# Deaths":26,"Child Mortality Rate":63.39},"Infant Mortality":{"# Deaths":23,"Infant Mortality Rate":6.41},"Frequent Physical Distress":{"% Frequent Physical Distress":13.5},"Frequent Mental Distress":{"% Frequent Mental Distress":17.6},"Diabetes Prevalence":{"% Adults with Diabetes":12.2},"HIV Prevalence":{"# HIV Cases":204,"HIV Prevalence Rate":449.1},"Food Insecurity":{"# Food Insecure":9150,"% Food Insecure":18.2},"Limited Access to Healthy Foods":{"# Limited Access to Healthy Foods":2284.23,"% Limited Access to Healthy Foods":5.03},"Drug Overdose Deaths":{"# Drug Overdose Deaths":23,"Drug Overdose Mortality Rate":14.9},"Insufficient Sleep":{"% Insufficient Sleep":38.4},"Uninsured Adults":{"# Uninsured Adults":6330,"% Uninsured Adults":22.37},"Uninsured Children":{"# Uninsured Children":1476,"% Uninsured Children":13.66},"Other Primary Care Providers":{"Other Primary Care Provider Rate":55.88,"Other Primary Care Provider Ratio":"1790:1"},"High School Graduation":{"Cohort Size":"","High School Graduation Rate":""},"Disconnected Youth":{"% Disconnected Youth":15.84},"Reading Scores":{"Average Grade Performance":2.77},"Math Scores":{"Average Grade Performance":2.94},"School Segregation":{"Segregation Index":0.09},"School Funding Adequacy":{"Spending per Pupil":12012.17,"School Funding Adequacy":-3679.91},"Gender Pay Gap":{"Women's Median Earnings":33926,"Men's Median Earnings":51338,"Gender Pay Gap":0.66},"Median Household Income":{"Median Household Income":50827},"Children Eligible for Free or Reduced Price Lunch":{"% Enrolled in Free or Reduced Lunch":66},"Residential Segregation - Black/White":{"Segregation Index":47.03},"Child Care Cost Burden":{"% Household Income Required for Child Care Expenses":24.12},"Child Care Centers":{"# Child Care Centers":7,"Child Care Centers per 1,000 Children":2.72},"Homicides":{"Homicide Rate":9.29},"Suicides":{"# Deaths":61,"Suicide Rate, Age-Adjusted":24.15,"Crude Rate":24.26},"Firearm Fatalities":{"# Firearm Fatalities":62,"Firearm Fatalities Rate":24.66},"Motor Vehicle Crash Deaths":{"# Motor Vehicle Deaths":92,"Motor Vehicle Mortality Rate":26.7},"Juvenile Arrests":{"Non-Petitioned Cases":41,"Petitioned Cases":47,"Denominator":4100,"Juvenile Arrest Rate":21.46},"Voter Turnout":{"% Voter Turnout":63.45},"Census Participation":{"% Census Participation":43.6},"Traffic Volume":{"Traffic Volume":83.15},"Homeownership":{"# Homeowners":13338,"% Homeowners":78.33},"Severe Housing Cost Burden":{"# Households with Severe Cost Burden":1655,"% Households with Severe Cost Burden":10.26},"Broadband Access":{"% Households with Broadband Access":80.61,"# Households with Broadband Access":13726},"Population":{"Population":51899},"% Below 18 Years of Age":{"% Less than 18 Years of Age":20.26},"% 65 and Older":{"% 65 and Over":18.97},"% Non-Hispanic Black":{"# Black":4754,"% Black":9.16},"% American Indian or Alaska Native":{"# American Indian or Alaska Native":1181,"% American Indian or Alaska Native":2.28},"% Asian":{"# Asian":475,"% Asian":0.92},"% Native Hawaiian or Other Pacific Islander":{"# Native Hawaiian or Other Pacific Islander":62,"% Native Hawaiian or Other Pacific Islander":0.12},"% Hispanic":{"# Hispanic":8119,"% Hispanic":15.64},"% Non-Hispanic White":{"# Non-Hispanic White":36912,"% Non-Hispanic White":71.12},"% Not Proficient in English":{"# Not Proficient in English":867,"% Not Proficient in English":1.85},"% Female":{"% Female":46.05},"% Rural":{"# Rural Residents":35258,"% Rural":77.64}}