{"About":{"FIPS":"54043","State":"West Virginia","Population":"","County":"Lincoln"},"Premature Death":{"Unreliable":"","Deaths":536,"Years of Potential Life Lost Rate":15465.33},"Poor or Fair Health":{"% Fair or Poor Health":24.4},"Poor Physical Health Days":{"Average Number of Physically Unhealthy Days":5.27},"Poor Mental Health Days":{"Average Number of Mentally Unhealthy Days":6.4},"Low Birthweight":{"Unreliable":"","% Low Birthweight":10.74},"Adult Smoking":{"% Adults Reporting Currently Smoking":28},"Adult Obesity":{"% Adults with Obesity":43.3},"Food Environment Index":{"Food Environment Index":7.4},"Physical Inactivity":{"% Physically Inactive":35},"Access to Exercise Opportunities":{"% With Access to Exercise Opportunities":5.12},"Excessive Drinking":{"% Excessive Drinking":12.75},"Alcohol-Impaired Driving Deaths":{"# Alcohol-Impaired Driving Deaths":5,"# Driving Deaths":20,"% Driving Deaths with Alcohol Involvement":25},"Sexually Transmitted Infections":{"# Chlamydia Cases":47,"Chlamydia Rate":230.3},"Teen Births":{"Teen Birth Rate":39.94},"Uninsured":{"Number of Uninsured":1235,"Percent of Total Population Uninsured":7.89},"Primary Care Physicians":{"# Primary Care Physicians":9,"Primary Care Physicians Rate":44.9,"Primary Care Physicians Ratio":"2227:1"},"Dentists":{"# Dentists":4,"Dentist Rate":19.87,"Dentist Ratio":"5032:1"},"Mental Health Providers":{"# Mental Health Providers":13,"Mental Health Provider Rate":64.59,"Mental Health Provider Ratio":"1548:1"},"Preventable Hospital Stays":{"Preventable Hospitalization Rate":4828},"Mammography Screening":{"% with Annual Mammogram":25},"Flu Vaccinations":{"% Vaccinated":41},"High School Completion":{"# Completed High School":11850,"Population":14632,"% Completed High School":80.99},"Some College":{"# Some College":2368,"Population":4752,"% Some College":49.83},"Unemployment":{"# Unemployed":465,"Labor Force":7086,"% Unemployed":6.56},"Children in Poverty":{"% Children in Poverty":26.7},"Income Inequality":{"80th Percentile Income":82544,"20th Percentile Income":16364,"Income Ratio":5.04},"Children in Single-Parent Households":{"# Children in Single-Parent Households":757,"# Children in Households":4621,"% Children in Single-Parent Households":16.38},"Social Associations":{"# Associations":7,"Social Association Rate":3.49},"Injury Deaths":{"# Injury Deaths":176,"Injury Death Rate":170.69},"Air Pollution - Particulate Matter":{"Average Daily PM2.5":8},"Drinking Water Violations":{"Presence of Water Violation":"No"},"Severe Housing Problems":{"% Severe Housing Problems":10.41,"Severe Housing Cost Burden":8.01,"Overcrowding":1.89,"Inadequate Facilities":1.04},"Driving Alone to Work":{"% Drive Alone to Work":83.55},"Long Commute - Driving Alone":{"# Workers who Drive Alone":6360,"% Long Commute - Drives Alone":67},"Life Expectancy":{"Life Expectancy":70.8},"Premature Age-Adjusted Mortality":{"# Deaths":536,"Age-Adjusted Death Rate":696.72},"Child Mortality":{"# Deaths":13,"Child Mortality Rate":71.52},"Infant Mortality":{"# Deaths":"","Infant Mortality Rate":""},"Frequent Physical Distress":{"% Frequent Physical Distress":16.2},"Frequent Mental Distress":{"% Frequent Mental Distress":20.7},"Diabetes Prevalence":{"% Adults with Diabetes":13.2},"HIV Prevalence":{"# HIV Cases":9,"HIV Prevalence Rate":53.2},"Food Insecurity":{"# Food Insecure":3390,"% Food Insecure":16.4},"Limited Access to Healthy Foods":{"# Limited Access to Healthy Foods":250.54,"% Limited Access to Healthy Foods":1.15},"Drug Overdose Deaths":{"# Drug Overdose Deaths":41,"Drug Overdose Mortality Rate":67.16},"Insufficient Sleep":{"% Insufficient Sleep":42.3},"Uninsured Adults":{"# Uninsured Adults":1093,"% Uninsured Adults":9.58},"Uninsured Children":{"# Uninsured Children":153,"% Uninsured Children":3.45},"Other Primary Care Providers":{"Other Primary Care Provider Rate":84.47,"Other Primary Care Provider Ratio":"1184:1"},"High School Graduation":{"Cohort Size":211,"High School Graduation Rate":92},"Disconnected Youth":{"% Disconnected Youth":""},"Reading Scores":{"Average Grade Performance":2.67},"Math Scores":{"Average Grade Performance":2.53},"School Segregation":{"Segregation Index":""},"School Funding Adequacy":{"Spending per Pupil":12836,"School Funding Adequacy":1681.98},"Gender Pay Gap":{"Women's Median Earnings":37321,"Men's Median Earnings":55303,"Gender Pay Gap":0.67},"Median Household Income":{"Median Household Income":41452},"Children Eligible for Free or Reduced Price Lunch":{"% Enrolled in Free or Reduced Lunch":57.13},"Residential Segregation - Black/White":{"Segregation Index":""},"Child Care Cost Burden":{"% Household Income Required for Child Care Expenses":42.44},"Child Care Centers":{"# Child Care Centers":2,"Child Care Centers per 1,000 Children":1.79},"Homicides":{"Homicide Rate":""},"Suicides":{"# Deaths":25,"Suicide Rate, Age-Adjusted":25.99,"Crude Rate":24.25},"Firearm Fatalities":{"# Firearm Fatalities":21,"Firearm Fatalities Rate":20.37},"Motor Vehicle Crash Deaths":{"# Motor Vehicle Deaths":32,"Motor Vehicle Mortality Rate":21.91},"Juvenile Arrests":{"Non-Petitioned Cases":"1-4","Petitioned Cases":11,"Denominator":2100,"Juvenile Arrest Rate":""},"Voter Turnout":{"% Voter Turnout":49.17},"Census Participation":{"% Census Participation":43},"Traffic Volume":{"Traffic Volume":3.99},"Homeownership":{"# Homeowners":6175,"% Homeowners":79.58},"Severe Housing Cost Burden":{"# Households with Severe Cost Burden":754,"% Households with Severe Cost Burden":10.84},"Broadband Access":{"% Households with Broadband Access":79.7,"# Households with Broadband Access":6184},"Population":{"Population":20126},"% Below 18 Years of Age":{"% Less than 18 Years of Age":22.23},"% 65 and Older":{"% 65 and Over":20.48},"% Non-Hispanic Black":{"# Black":81,"% Black":0.4},"% American Indian or Alaska Native":{"# American Indian or Alaska Native":26,"% American Indian or Alaska Native":0.13},"% Asian":{"# Asian":64,"% Asian":0.32},"% Native Hawaiian or Other Pacific Islander":{"# Native Hawaiian or Other Pacific Islander":1,"% Native Hawaiian or Other Pacific Islander":0},"% Hispanic":{"# Hispanic":156,"% Hispanic":0.78},"% Non-Hispanic White":{"# Non-Hispanic White":19557,"% Non-Hispanic White":97.17},"% Not Proficient in English":{"# Not Proficient in English":26,"% Not Proficient in English":0.13},"% Female":{"% Female":50.2},"% Rural":{"# Rural Residents":21720,"% Rural":100}}